density_probability/Binomialdistribution.py
density_probability/Gaussiandistribution.py
density_probability/Generaldistribution.py
density_probability/__init__.py
density_probability-0.1.dist-info/METADATA
density_probability-0.1.dist-info/WHEEL
density_probability-0.1.dist-info/top_level.txt
density_probability-0.1.dist-info/RECORD
