Metadata-Version: 2.1
Name: density-probability
Version: 0.1
Summary: Gaussian and Binomial distributions
Home-page: UNKNOWN
Author: Franck Tchamo
Author-email: francktchamo@gmail.com
License: UNKNOWN
Platform: UNKNOWN
